hostman/__init__.py
hostman/utils.py
pyhostman-0.1.3.dist-info/LICENSE
pyhostman-0.1.3.dist-info/METADATA
pyhostman-0.1.3.dist-info/WHEEL
pyhostman-0.1.3.dist-info/entry_points.txt
pyhostman-0.1.3.dist-info/top_level.txt
pyhostman-0.1.3.dist-info/RECORD
