Metadata-Version: 2.1
Name: pyhostman
Version: 0.1.3
Summary: A CLI to manage a hosts file
Home-page: http://github.com/jonhadfield/hostman
Author: Jon Hadfield
Author-email: jon.hadfield@lessknown.co.uk
License: MIT
Keywords: hosts,Python,network
Platform: any
Classifier: Programming Language :: Python
Classifier: Development Status :: 2 - Pre-Alpha
Classifier: Natural Language :: English
Classifier: Environment :: Console
Classifier: Intended Audience :: System Administrators
Classifier: License :: OSI Approved :: MIT License
Classifier: Operating System :: OS Independent
Classifier: Topic :: System :: Operating System
Classifier: Topic :: System :: Networking
Requires-Dist: docopt (>=0.6.2)
Requires-Dist: colorama (>=0.3.3)
Requires-Dist: python-hosts (>=0.4.7)
